{
	"autofit":false,
	"fleetDataId":"bv_tritachyon_ranged",
	"minDP":70,
	"maxDP":500,
	"defaultFleetWidePersonality":"steady",
	"spawnIfNoIndustry":false,
	"autoLogitsticsFreighterDP":0.02,
	"autoLogitsticsTankerDP":0.02,
	"fleetPartitions":[
		{
			"partitionWeight":55,
			"variants":{
				"paragon_Elite_bv":30,
				"paragon_Escort_bv":30,
				"astral_Strike_bv":15,
				"astral_Elite_bv":15,
				"doom_Support_bv":10
			}
		},
		{
			"partitionWeight":35,
			"variants":{
				"eagle_Balanced_bv":60.00,
				"sunder_Support_bv":40.00
			}
		},
		{
			"partitionWeight":10,
			"variants":{
				"omen_Ew_bv":16.39,
				"tempest_Attack1_bv":16.39,
				"tempest_Attack2_bv":16.39,
				"tempest_Attack3_bv":16.39,
				"brawler_tritachyon_Standard1_bv":11.48,
				"brawler_tritachyon_Standard2_bv":11.48,
				"brawler_tritachyon_Support_bv":11.48
			}
		}
	]
}

